MANIFEST.in
README.md
setup.py
django_semanticui_forms.egg-info/PKG-INFO
django_semanticui_forms.egg-info/SOURCES.txt
django_semanticui_forms.egg-info/dependency_links.txt
django_semanticui_forms.egg-info/requires.txt
django_semanticui_forms.egg-info/top_level.txt
semanticuiforms/__init__.py
semanticuiforms/fields.py
semanticuiforms/models.py
semanticuiforms/tests.py
semanticuiforms/utils.py
semanticuiforms/wrappers.py
semanticuiforms/management/__init__.py
semanticuiforms/management/commands/__init__.py
semanticuiforms/management/commands/semanticuivalidation.py
semanticuiforms/static/suiforms/filefield.js
semanticuiforms/templatetags/__init__.py
semanticuiforms/templatetags/semanticui.py