Metadata-Version: 1.0
Name: django-semanticui-forms
Version: 1.6.5
Summary: Effortlessly style all of your Django forms and form fields with Semantic UI wrappers.
Home-page: https://github.com/thetarkus/django-semanticui-forms
Author: Michael
Author-email: thetarkus@users.noreply.github.com
License: UNKNOWN
Platform: UNKNOWN
